<annotation>
	<folder>images</folder>
	<filename>i (187).jpg</filename>
	<path>E:\images\i (187).jpg</path>
	<source>
		<database>Unknown</database>
	</source>
	<size>
		<width>0</width>
		<height>0</height>
		<depth>3</depth>
	</size>
	<segmented>0</segmented>
	<object>
		<name>private_hause</name>
		<pose>Unspecified</pose>
		<truncated>0</truncated>
		<difficult>0</difficult>
		<bndbox>
			<xmin>45</xmin>
			<ymin>40</ymin>
			<xmax>369</xmax>
			<ymax>238</ymax>
		</bndbox>
	</object>
</annotation>
